tipyverse/__init__.py
tipyverse/conflicts.py
tipyverse/data_import.py
tipyverse/data_manipulation.py
tipyverse/data_tidy.py
tipyverse/data_visualization.py
tipyverse/functional.py
tipyverse/utilities.py
tipyverse-0.0.2.1.dist-info/LICENSE
tipyverse-0.0.2.1.dist-info/METADATA
tipyverse-0.0.2.1.dist-info/WHEEL
tipyverse-0.0.2.1.dist-info/top_level.txt
tipyverse-0.0.2.1.dist-info/RECORD
