Metadata-Version: 2.1
Name: tipyverse
Version: 0.0.2.1
Summary: A package to install Python equivalents of R tipyverse packages
Author-email: Sebastian Dunn <sebastiandunn@sdmdigital.co>
License: MIT License
Project-URL: Homepage, https://github.com/axolmain/Tipyverse
Project-URL: Issues, https://github.com/axolmain/Tipyverse/issues
Project-URL: Repository, https://github.com/axolmain/Tipyverse.git
Keywords: tipyverse,R,data science,python
Classifier: Programming Language :: Python :: 3
Classifier: License :: OSI Approved :: MIT License
Classifier: Operating System :: OS Independent
Requires-Python: >=3.8
License-File: LICENSE
Requires-Dist: lets-plot
Requires-Dist: siuba
Requires-Dist: swifter
Requires-Dist: sqlalchemy
Requires-Dist: mysql-connector-python
Requires-Dist: pyreadstat
Requires-Dist: requests
Requires-Dist: google-api-python-client
Requires-Dist: google-auth-httplib2
Requires-Dist: google-auth-oauthlib
Requires-Dist: pydrive2
Requires-Dist: beautifulsoup4
Requires-Dist: lxml
Requires-Dist: playwright
Requires-Dist: toolz
Requires-Dist: polars
Requires-Dist: fastapi
Requires-Dist: dask
Requires-Dist: plotnine
Requires-Dist: seaborn
Requires-Dist: numpy
Requires-Dist: scipy
Requires-Dist: statsmodels
Requires-Dist: altair
Provides-Extra: groupby
Requires-Dist: swifter ; extra == 'groupby'
Provides-Extra: notebook
Requires-Dist: swifter ; extra == 'notebook'
